WrightSim/VERSION
WrightSim/__init__.py
WrightSim/__version__.py
WrightSim/integration.py
WrightSim/measure.py
WrightSim/response.py
WrightSim/driven/__init__.py
WrightSim/experiment/__init__.py
WrightSim/experiment/_axis.py
WrightSim/experiment/_experiment.py
WrightSim/experiment/_pulse.py
WrightSim/experiment/_scan.py
WrightSim/hamiltonian/TRSF_default.py
WrightSim/hamiltonian/__init__.py
WrightSim/hamiltonian/default.py
WrightSim/mixed/__init__.py
WrightSim/mixed/propagate.py
WrightSim/mixed/system.py
tests/__init__.py
tests/import.py
WrightSim-0.1.0.dist-info/LICENSE
WrightSim-0.1.0.dist-info/METADATA
WrightSim-0.1.0.dist-info/WHEEL
WrightSim-0.1.0.dist-info/top_level.txt
WrightSim-0.1.0.dist-info/RECORD
